MANIFEST.in
README.md
VERSION
setup.py
adminlte3/__init__.py
adminlte3/admin.py
adminlte3/apps.py
adminlte3/compat.py
adminlte3/models.py
adminlte3/tests.py
adminlte3/views.py
adminlte3/migrations/__init__.py
adminlte3/static/admin-lte/.babelrc
adminlte3/static/admin-lte/.browserslistrc
adminlte3/static/admin-lte/.editorconfig
adminlte3/static/admin-lte/.eslintignore
adminlte3/static/admin-lte/.eslintrc
adminlte3/static/admin-lte/.travis.yml
adminlte3/static/admin-lte/LICENSE
adminlte3/static/admin-lte/README.md
adminlte3/static/admin-lte/composer.json
adminlte3/static/admin-lte/index.html
adminlte3/static/admin-lte/index2.html
adminlte3/static/admin-lte/index3.html
adminlte3/static/admin-lte/package-lock.json
adminlte3/static/admin-lte/package.json
adminlte3/static/admin-lte/starter.html
adminlte3/static/admin-lte/.github/ISSUE_TEMPLATE/bug-report-for-adminlte-v2-4-x.md
adminlte3/static/admin-lte/.github/ISSUE_TEMPLATE/bug-report-for-adminlte-v3-x.md
adminlte3/static/admin-lte/.github/ISSUE_TEMPLATE/feature-request-for-adminlte-v3-x.md
adminlte3/static/admin-lte/dist/css/adminlte.css
adminlte3/static/admin-lte/dist/css/adminlte.css.map
adminlte3/static/admin-lte/dist/css/adminlte.min.css
adminlte3/static/admin-lte/dist/css/adminlte.min.css.map
adminlte3/static/admin-lte/dist/css/alt/adminlte.components.css
adminlte3/static/admin-lte/dist/css/alt/adminlte.components.css.map
adminlte3/static/admin-lte/dist/css/alt/adminlte.components.min.css
adminlte3/static/admin-lte/dist/css/alt/adminlte.components.min.css.map
adminlte3/static/admin-lte/dist/css/alt/adminlte.core.css
adminlte3/static/admin-lte/dist/css/alt/adminlte.core.css.map
adminlte3/static/admin-lte/dist/css/alt/adminlte.core.min.css
adminlte3/static/admin-lte/dist/css/alt/adminlte.core.min.css.map
adminlte3/static/admin-lte/dist/css/alt/adminlte.extra-components.css
adminlte3/static/admin-lte/dist/css/alt/adminlte.extra-components.css.map
django_adminlte_3.egg-info/PKG-INFO
django_adminlte_3.egg-info/SOURCES.txt
django_adminlte_3.egg-info/dependency_links.txt
django_adminlte_3.egg-info/requires.txt
django_adminlte_3.egg-info/top_level.txt